pyLAD/Base.py
pyLAD/Mapping.py
pyLAD/Parser.py
pyLAD/Segmenter.py
pyLAD/__init__.py
pyLAD/dnacopy.so
pyLAD/string_trimming.so
pyLAD/version.py
pyLAD/pyLAD/__init__.py
pyLAD-1.0.0.data/scripts/LADetector
pyLAD-1.0.0.dist-info/METADATA
pyLAD-1.0.0.dist-info/WHEEL
pyLAD-1.0.0.dist-info/top_level.txt
pyLAD-1.0.0.dist-info/RECORD
