Metadata-Version: 2.1
Name: pyLAD
Version: 1.0.0
Summary: pyLAD: Python-based DamID Lamina-Associated-Domain analysis
Home-page: https://github.com/thereddylab/pyLAD
Maintainer: Michael Sauria
Maintainer-email: mike.sauria@gmail.com
License: BSD
Download-URL: https://github.com/thereddylab/pyLAD/tarball/1.0.0
Platform: Windows
Platform: Linux
Platform: Solaris
Platform: Mac OS-X
Platform: Unix
Classifier: Intended Audience :: Science/Research
Classifier: Intended Audience :: Developers
Classifier: Programming Language :: Fortran
Classifier: Programming Language :: Python
Classifier: Programming Language :: Python :: 3
Classifier: Topic :: Software Development
Classifier: Topic :: Scientific/Engineering
Classifier: Operating System :: Microsoft :: Windows
Classifier: Operating System :: POSIX
Classifier: Operating System :: Unix
Classifier: Operating System :: MacOS
Requires-Dist: numpy
Requires-Dist: scipy
Requires-Dist: pysam
